cyrius/__init__.py
cyrius/__main__.py
cyrius/star_caller.py
cyrius/caller/__init__.py
cyrius/caller/call_variants.py
cyrius/caller/cnv_hybrid.py
cyrius/caller/construct_star_table.py
cyrius/caller/match_star_allele.py
cyrius/data/CYP2D6_SNP_19.txt
cyrius/data/CYP2D6_SNP_37.txt
cyrius/data/CYP2D6_SNP_38.txt
cyrius/data/CYP2D6_gmm.txt
cyrius/data/CYP2D6_haplotype_19.txt
cyrius/data/CYP2D6_haplotype_37.txt
cyrius/data/CYP2D6_haplotype_38.txt
cyrius/data/CYP2D6_region_19.bed
cyrius/data/CYP2D6_region_37.bed
cyrius/data/CYP2D6_region_38.bed
cyrius/data/CYP2D6_target_variant_19.txt
cyrius/data/CYP2D6_target_variant_37.txt
cyrius/data/CYP2D6_target_variant_38.txt
cyrius/data/CYP2D6_target_variant_homology_region_19.txt
cyrius/data/CYP2D6_target_variant_homology_region_37.txt
cyrius/data/CYP2D6_target_variant_homology_region_38.txt
cyrius/data/star_table.txt
cyrius/depth_calling/__init__.py
cyrius/depth_calling/bin_count.py
cyrius/depth_calling/copy_number_call.py
cyrius/depth_calling/gmm.py
cyrius/depth_calling/haplotype.py
cyrius/depth_calling/snp_count.py
cyrius/depth_calling/utilities.py
cyrius-1.1.1.dist-info/METADATA
cyrius-1.1.1.dist-info/RECORD
cyrius-1.1.1.dist-info/WHEEL
cyrius-1.1.1.dist-info/entry_points.txt
cyrius-1.1.1.dist-info/top_level.txt
