Metadata-Version: 2.1
Name: cyrius
Version: 1.1.1
Summary: WGS-based CYP2D6 caller
Home-page: https://github.com/illumina/Cyrius
Author: Xiao Chen
Author-email: xchen2@illumina.com
License: PolyFormStrict
Keywords: CYP2D6
Platform: UNKNOWN
Requires-Dist: pysam
Requires-Dist: numpy
Requires-Dist: scipy
Requires-Dist: statsmodels
